markov_chain/__init__.py
markov_chain/py.typed
markov_chain/small_language_model.py
markov_chain/small_language_model2.py
markov_chain_1-0.1.0.dist-info/METADATA
markov_chain_1-0.1.0.dist-info/WHEEL
markov_chain_1-0.1.0.dist-info/top_level.txt
markov_chain_1-0.1.0.dist-info/RECORD
