Metadata-Version: 2.1
Name: markov-chain-1
Version: 0.1.0
Summary: A simple Markov chain implementation
Requires-Python: >=3.12
